timeout_timer/__init__.py
timeout_timer/timeout_timer.py
timeout_timer-0.2.0.dist-info/LICENSE.txt
timeout_timer-0.2.0.dist-info/METADATA
timeout_timer-0.2.0.dist-info/WHEEL
timeout_timer-0.2.0.dist-info/top_level.txt
timeout_timer-0.2.0.dist-info/RECORD
