Metadata-Version: 2.1
Name: timeout-timer
Version: 0.2.0
Summary: Timeout timer use signal or thread module, support nested loop
Home-page: https://github.com/dozysun/timeout-timer
Author: dozysun
Author-email: dozysun@gmail.com
License: UNKNOWN
Platform: UNKNOWN
Classifier: Development Status :: 4 - Beta
Classifier: Intended Audience :: Developers
Classifier: License :: OSI Approved :: MIT License
Classifier: Programming Language :: Python :: 3
Classifier: Programming Language :: Python :: 3.6
Classifier: Programming Language :: Python :: 3.7
Classifier: Programming Language :: Python :: 3.8
Classifier: Programming Language :: Python :: 3.9
Classifier: Programming Language :: Python :: 3 :: Only
License-File: LICENSE.txt
